<?xml version="1.0" encoding="ISO-8859-1"?>
<!DOCTYPE symbol-and-basic-behavior-files SYSTEM "../symbol-and-basic-behavior-files.dtd">
<option xmlns="http://www.xabsl.de" xmlns:xsi="http://www.w3.org/2001/XMLSchema-instance" name="ballfound" initial-state="ballfound">
  &mySymbols;
  &myBasicBehaviors;
  &options;
  <common-decision-tree>
    <if>
      <condition description="">
        <enumerated-input-symbol-comparison>
          <enumerated-input-symbol-ref ref="ballreturn"/>
          <enum-element-ref ref="BallReturns.BALLFOUND"/>
        </enumerated-input-symbol-comparison>
      </condition>
      <transition-to-state ref="ballfound"/>
    </if>
    <else>
      <if>
        <condition description="">
          <not>
            <enumerated-input-symbol-comparison>
              <enumerated-input-symbol-ref ref="ballreturn"/>
              <enum-element-ref ref="BallReturns.BALLFOUND"/>
            </enumerated-input-symbol-comparison>
          </not>
        </condition>
        <transition-to-state ref="noball"/>
      </if>
    </else>
  </common-decision-tree>
  <state name="ballfound">
    <subsequent-basic-behavior ref="doMakePath"/>
    <subsequent-option ref="checkpath"/>
    <decision-tree>
      <transition-to-state ref="ballfound"/>
    </decision-tree>
  </state>
  <state name="noball">
    <decision-tree>
      <transition-to-state ref="noball"/>
    </decision-tree>
  </state>
</option>
